.gitignore
Dockerfile
README.md
__init__.py
docker-compose.yml
manage.py
pyproject.toml
arches_her/.babelrc
arches_her/.browserslistrc
arches_her/.eslintignore
arches_her/.eslintrc.js
arches_her/.stylelintrc.json
arches_her/.yarnrc
arches_her/__init__.py
arches_her/celery.py
arches_her/package.json
arches_her/settings.py
arches_her/settings_docker.py
arches_her/settings_local.py
arches_her/urls.py
arches_her/wsgi.py
arches_her/yarn.lock
arches_her.egg-info/PKG-INFO
arches_her.egg-info/SOURCES.txt
arches_her.egg-info/dependency_links.txt
arches_her.egg-info/requires.txt
arches_her.egg-info/top_level.txt
arches_her/datatypes/__init__.py
arches_her/datatypes/bngcentrepoint.py
arches_her/docx/Blank Adviser Letter.docx
arches_her/docx/Condition Historic Building Recording Letter.docx
arches_her/docx/Condition Investigation Letter.docx
arches_her/docx/Condition Satisfied Letter.docx
arches_her/docx/Condition Two-Stage Letter.docx
arches_her/docx/No Need to Consult letter.docx
arches_her/docx/No progression letter.docx
arches_her/docx/Post Excavation Assessment Approval Letter.docx
arches_her/docx/Pre-App Recommend Condition Letter.docx
arches_her/docx/Pre-app Predetermination letter.docx
arches_her/docx/Predetermination Letter.docx
arches_her/docx/WSI Amend Letter.docx
arches_her/docx/WSI Approval Letter.docx
arches_her/functions/__init__.py
arches_her/functions/bngpoint_to_geojson_function.py
arches_her/functions/consultation_status_function.py
arches_her/functions/generate_unique_references_function.py
arches_her/functions/geojson_to_bngpoint_function.py
arches_her/logs/.gitkeep
arches_her/management/__init__.py
arches_her/management/commands/__init__.py
arches_her/management/commands/docx.py
arches_her/media/build/.gitignore
arches_her/media/css/_project-breakpoints.scss
arches_her/media/css/_project-functions.scss
arches_her/media/css/_project-variables.scss
arches_her/media/css/accessibility-plugin.css
arches_her/media/css/bng-filter.css
arches_her/media/css/consultations.css
arches_her/media/css/project-README.md
arches_her/media/css/project.css
arches_her/media/css/project.scss
arches_her/media/css/report_templates.css
